JoyMondalSIG/__init__.py
JoyMondalSIG-0.1.dist-info/METADATA
JoyMondalSIG-0.1.dist-info/WHEEL
JoyMondalSIG-0.1.dist-info/top_level.txt
JoyMondalSIG-0.1.dist-info/RECORD
