Metadata-Version: 2.1
Name: JoyMondalSIG
Version: 0.1
Summary: A Python package to gather system information and check Python installation.
Home-page: https://github.com/codewithjoymondal/JoyMondalSIG
Author: Joy Mondal
Author-email: Contact.Joymondal@email.com
Classifier: Programming Language :: Python :: 3.10
Classifier: License :: OSI Approved :: MIT License
Classifier: Operating System :: OS Independent
